MANIFEST.in
README.md
setup.py
eboshi/__init__.py
eboshi/add_cron_schedule.py
eboshi/add_schedule.py
eboshi/create_project.py
eboshi/delete_project.py
eboshi/exec.py
eboshi/fetch_flow.py
eboshi/get_most_recent_next_exec_time.py
eboshi/get_schedule.py
eboshi/list_schedules.py
eboshi/main.py
eboshi/project.py
eboshi/remove_all_schedules.py
eboshi/remove_schedule.py
eboshi/schedule.py
eboshi/session.py
eboshi/upload.py
eboshi.egg-info/PKG-INFO
eboshi.egg-info/SOURCES.txt
eboshi.egg-info/dependency_links.txt
eboshi.egg-info/entry_points.txt
eboshi.egg-info/requires.txt
eboshi.egg-info/top_level.txt