Metadata-Version: 2.1
Name: eboshi
Version: 0.0.17
Summary: Azkaban CLI tool
Home-page: https://github.com/wyukawa/eboshi
Author: wyukawa
Author-email: wyukawa@gmail.com
License: MIT
Platform: UNKNOWN
Classifier: Development Status :: 3 - Alpha
Classifier: Intended Audience :: Developers
Classifier: License :: OSI Approved :: MIT License
Classifier: Programming Language :: Python
Classifier: Programming Language :: Python :: 2.7
Classifier: Environment :: Console
